da_fits_warp/__init__.py
da_fits_warp/da_fits_warp.py
da_fits_warp-2.1.2.dist-info/METADATA
da_fits_warp-2.1.2.dist-info/WHEEL
da_fits_warp-2.1.2.dist-info/entry_points.txt
da_fits_warp-2.1.2.dist-info/RECORD
