Metadata-Version: 2.1
Name: da-fits-warp
Version: 2.1.2
Summary: Warp catalogues and images to remove the distorting affect of the ionosphere.
License: AFL-3.0
Author: Natasha Hurley-Walker, Paul Hancock, Tim Galvin
Requires-Python: >=3.8,<4.0
Classifier: License :: OSI Approved :: Academic Free License (AFL)
Classifier: Programming Language :: Python :: 3
Classifier: Programming Language :: Python :: 3.8
Classifier: Programming Language :: Python :: 3.9
Classifier: Programming Language :: Python :: 3.10
Classifier: Programming Language :: Python :: 3.11
Requires-Dist: astropy (>=5.2.1,<6.0.0)
Requires-Dist: dask[distributed] (>=2023.2.0,<2024.0.0)
Requires-Dist: matplotlib (>=3.7.0,<4.0.0)
Requires-Dist: numpy (>=1.23.0,<2.0.0)
Requires-Dist: scipy (>=1.9.0,<2.0.0)
